LICENSE
MANIFEST.in
README.rst
setup.py
replica/__init__.py
replica/cli.py
replica/cloner.py
replica/tagger.py
replica.egg-info/PKG-INFO
replica.egg-info/SOURCES.txt
replica.egg-info/dependency_links.txt
replica.egg-info/entry_points.txt
replica.egg-info/requires.txt
replica.egg-info/top_level.txt