Metadata-Version: 1.2
Name: replica
Version: 0.1.2
Summary: id3 metadata file cloner
Home-page: https://github.com/KraYmer/replica
Author: Fabrice Laporte
Author-email: kraymer@gmail.com
License: MIT
Platform: ALL
Classifier: Topic :: Multimedia :: Sound/Audio
Classifier: Topic :: Multimedia :: Sound/Audio :: Players :: MP3
Classifier: License :: OSI Approved :: MIT License
Classifier: Environment :: Console
Requires-Python: >=2.6, <4
